lod/__init__.py
lod/client.py
lod/manager.py
lod/proxy.py
lod/runner.py
locust_on_databricks-0.2.1.dist-info/LICENSE
locust_on_databricks-0.2.1.dist-info/METADATA
locust_on_databricks-0.2.1.dist-info/WHEEL
locust_on_databricks-0.2.1.dist-info/top_level.txt
locust_on_databricks-0.2.1.dist-info/RECORD
