Metadata-Version: 2.2
Name: locust-on-databricks
Version: 0.2.1
Summary: Run locust on single node or distributed on Databricks.
Home-page: https://github.com/stikkireddy/locust-on-databricks
Author: Sri Tikkireddy
Author-email: sri.tikkireddy@databricks.com
Classifier: Programming Language :: Python :: 3
Classifier: Operating System :: OS Independent
Requires-Python: >=3.11
License-File: LICENSE
Requires-Dist: locust<3.0,>=2.33
Requires-Dist: psutil<8.0,>=7.0
Provides-Extra: dev
Requires-Dist: pytest; extra == "dev"
Requires-Dist: pytest-pep8; extra == "dev"
Requires-Dist: pytest-cov; extra == "dev"
Requires-Dist: pyspark==3.4.1; extra == "dev"
Requires-Dist: twine; extra == "dev"
Dynamic: author
Dynamic: author-email
Dynamic: classifier
Dynamic: description
Dynamic: description-content-type
Dynamic: home-page
Dynamic: provides-extra
Dynamic: requires-dist
Dynamic: requires-python
Dynamic: summary
